phasedist/__init__.py
phasedist/dist.py
phasedist/fit.py
phasedist/fitcph.py
phasedist/fitcph2dist.py
phasedist/fitdph.py
phasedist/__pycache__/__init__.cpython-310.pyc
phasedist/__pycache__/dist.cpython-310.pyc
phasedist/__pycache__/fit.cpython-310.pyc
phasedist/__pycache__/fitcph.cpython-310.pyc
phasedist/__pycache__/fitcph2dist.cpython-310.pyc
phasedist/__pycache__/fitdph.cpython-310.pyc
phasedist-0.1.2.dist-info/licenses/LICENSE
phasedist-0.1.2.dist-info/METADATA
phasedist-0.1.2.dist-info/WHEEL
phasedist-0.1.2.dist-info/top_level.txt
phasedist-0.1.2.dist-info/RECORD
