Metadata-Version: 2.4
Name: phasedist
Version: 0.1.2
Summary: Fit continuous and discrete phase-type distributions
Author-email: Anders Reenberg Andersen <andersra@live.dk>
Project-URL: Homepage, https://github.com/areenberg/phasedist
Project-URL: Issues, https://github.com/areenberg/phasedist/issues
Classifier: Development Status :: 3 - Alpha
Classifier: Programming Language :: Python :: 3
Classifier: License :: OSI Approved :: MIT License
Classifier: Operating System :: OS Independent
Requires-Python: >=3.10
License-File: LICENSE
Requires-Dist: numpy>=1.24.2
Requires-Dist: scipy>=1.10.1
Requires-Dist: matplotlib>=3.7.2
Requires-Dist: statsmodels>=0.14.4
Dynamic: license-file
